longchain/__init__.py
longchain/core/actionresolver.py
longchain/core/agentaction.py
longchain/core/dataclasses.py
longchain/core/datastore.py
longchain/core/messager.py
longchain/core/path.py
longchain/core/quest.py
longchain/impl/actionresolver/llm.py
longchain/impl/actionresolver/sequential.py
longchain/impl/agentaction/arbitrary.py
longchain/impl/agentaction/end.py
longchain/impl/agentaction/message.py
longchain/impl/datastore/jsonfile.py
longchain/impl/messager/slack.py
longchain/plugins/bag/__init__.py
longchain/plugins/bag/bag.py
longchain/plugins/bag/stake.py
longchain/plugins/bag/api/bag.proto
longchain/plugins/bag/api/bag_pb2.py
longchain/plugins/bag/api/bag_pb2.pyi
longchain/plugins/bag/api/bag_pb2_grpc.py
longchain-0.4.2.dist-info/METADATA
longchain-0.4.2.dist-info/WHEEL
longchain-0.4.2.dist-info/licenses/LICENSE
longchain-0.4.2.dist-info/RECORD
