Metadata-Version: 2.3
Name: longchain
Version: 0.4.2
Summary: A framework for LLM-powered interactions
Project-URL: Respository, https://github.com/rivques/longchain
License: Permission is hereby granted, free of charge, to any person obtaining a copy
License-File: LICENSE
Keywords: ai,chatbot,llm,npc,slack
Classifier: Development Status :: 4 - Beta
Classifier: License :: OSI Approved :: MIT License
Classifier: Operating System :: OS Independent
Classifier: Programming Language :: Python :: 3
Requires-Python: >=3.8
Provides-Extra: bag
Requires-Dist: grpcio; extra == 'bag'
Requires-Dist: grpcio-tools; extra == 'bag'
Provides-Extra: llm
Requires-Dist: openai; extra == 'llm'
Provides-Extra: slack
Requires-Dist: aiohttp; extra == 'slack'
Requires-Dist: slack-bolt; extra == 'slack'
Requires-Dist: slack-sdk; extra == 'slack'
